neoradio2.cp310-win32.pyd
neoradio2-1.3.1.dist-info/METADATA
neoradio2-1.3.1.dist-info/WHEEL
neoradio2-1.3.1.dist-info/RECORD
