Metadata-Version: 2.1
Name: neoradio2
Version: 1.3.1
Summary: neoRADIO2 python bindings
Keywords: intrepidcs,Automotive,ICS
Author-Email: David Rebbe <drebbe@intrepidcs.com>
Maintainer-Email: David Rebbe <drebbe@intrepidcs.com>
Classifier: Development Status :: 5 - Production/Stable
Classifier: Intended Audience :: Developers
Classifier: License :: OSI Approved :: MIT License
Classifier: Operating System :: OS Independent
Classifier: Topic :: Software Development :: Libraries :: Python Modules
Classifier: Programming Language :: Python
Classifier: Programming Language :: Python :: 3
Classifier: Programming Language :: Python :: 3.8
Classifier: Programming Language :: Python :: 3.9
Classifier: Programming Language :: Python :: 3.10
Classifier: Programming Language :: Python :: 3.11
Classifier: Programming Language :: Python :: 3.12
Classifier: Programming Language :: Python :: 3.13
Project-URL: Homepage, https://intrepidcs.com
Project-URL: Repository, https://github.com/intrepidcs/libneoradio2/
Project-URL: Issues, https://github.com/intrepidcs/libneoradio2/issues
Requires-Python: >=3.8
